vnlp/__init__.py
vnlp/data/__init__.py
vnlp/data/dataset.py
vnlp/data/datasplit.py
vnlp/data/example.py
vnlp/data/pipeline.py
vnlp/data/stage.py
vnlp/exp/__init__.py
vnlp/exp/grapher.py
vnlp/exp/tracker.py
vnlp/model/__init__.py
vnlp/model/model.py
vnlp/model/module.py
vnlp/nn/__init__.py
vnlp/nn/attention.py
vnlp/nn/functional.py
vnlp/nn/rnn.py
vnlp/utils/__init__.py
vnlp/utils/args.py
vnlp/utils/files.py
vnlp/utils/logging.py
vnlp/utils/process.py
vnlp-1.0.2.dist-info/METADATA
vnlp-1.0.2.dist-info/WHEEL
vnlp-1.0.2.dist-info/top_level.txt
vnlp-1.0.2.dist-info/RECORD
